oarepo_sitemaps/__init__.py
oarepo_sitemaps/ext.py
oarepo_sitemaps/version.py
oarepo_sitemaps-1.0.0.dist-info/LICENSE
oarepo_sitemaps-1.0.0.dist-info/METADATA
oarepo_sitemaps-1.0.0.dist-info/WHEEL
oarepo_sitemaps-1.0.0.dist-info/entry_points.txt
oarepo_sitemaps-1.0.0.dist-info/top_level.txt
oarepo_sitemaps-1.0.0.dist-info/RECORD
