Metadata-Version: 2.1
Name: oarepo-sitemaps
Version: 1.0.0
Summary: OARepo rdm records data model
Home-page: https://github.com/oarepo/oarepo-dc
Author: Alzbeta Pokorna
Author-email: alzbeta.pokorna@cesnet.cz
License: MIT
Platform: any
Classifier: Environment :: Web Environment
Classifier: Intended Audience :: Developers
Classifier: License :: OSI Approved :: MIT License
Classifier: Operating System :: OS Independent
Classifier: Programming Language :: Python
Classifier: Topic :: Internet :: WWW/HTTP :: Dynamic Content
Classifier: Topic :: Software Development :: Libraries :: Python Modules
Classifier: Programming Language :: Python :: 2
Classifier: Programming Language :: Python :: 2.7
Classifier: Programming Language :: Python :: 3
Classifier: Programming Language :: Python :: 3.5
Classifier: Development Status :: 4 - Beta
License-File: LICENSE
Requires-Dist: oarepo-mapping-includes
Requires-Dist: oarepo-records-draft
Requires-Dist: oarepo-communities
Requires-Dist: oarepo-invenio-model
Requires-Dist: flask-sitemap
Provides-Extra: tests
Requires-Dist: oarepo[tests] (~=3.3.0) ; extra == 'tests'
Requires-Dist: oarepo-records-draft ; extra == 'tests'
Requires-Dist: oarepo-actions ; extra == 'tests'
Requires-Dist: oarepo-validate ; extra == 'tests'
Requires-Dist: coverage ; extra == 'tests'
Requires-Dist: oarepo-mapping-includes ; extra == 'tests'
Requires-Dist: werkzeug (==1.0.1) ; extra == 'tests'
Requires-Dist: flask (==1.1.4) ; extra == 'tests'
